sharepp/__init__.py
sharepp/cmd.py
sharepp-1.1.3.dist-info/LICENSE
sharepp-1.1.3.dist-info/METADATA
sharepp-1.1.3.dist-info/WHEEL
sharepp-1.1.3.dist-info/entry_points.txt
sharepp-1.1.3.dist-info/RECORD
