Metadata-Version: 2.1
Name: sharepp
Version: 1.1.3
Summary: Library for getting ETF and cryptocurrency prices.
License: Apache-2.0
Author: Lukas Brauckmann
Author-email: lukas.brauckmann@gmail.com
Requires-Python: >=3.10,<4.0
Classifier: License :: OSI Approved :: Apache Software License
Classifier: Programming Language :: Python :: 3
Classifier: Programming Language :: Python :: 3.10
Classifier: Programming Language :: Python :: 3.11
Classifier: Programming Language :: Python :: 3.12
Requires-Dist: bs4 (>=0.0.1,<0.0.3)
Requires-Dist: currencyconverter (>=0.17.16,<0.18.0)
Requires-Dist: requests (>=2.28.2,<3.0.0)
